{"id":226,"name":"MANTINE","gender":"equal","baseStats":[65,40,70,80,140,70],"experienceType":"slow","experienceYield":168,"type1":"water","type2":"flying","eggGroups":["water1"],"eggCycles":25,"catchRate":25,"wildFleeRate":0.0,"moves":[{"name":"TACKLE","level":1,"tm":false,"breeding":false},{"name":"BUBBLE","level":1,"tm":false,"breeding":false},{"name":"SUPERSONIC","level":10,"tm":false,"breeding":false},{"name":"BUBBLEBEAM","level":18,"tm":false,"breeding":false},{"name":"TAKE DOWN","level":25,"tm":false,"breeding":false},{"name":"AGILITY","level":32,"tm":false,"breeding":false},{"name":"WING ATTACK","level":40,"tm":false,"breeding":false},{"name":"CONFUSE RAY","level":49,"tm":false,"breeding":false},{"name":"HEADBUTT","level":0,"tm":true,"breeding":false},{"name":"CURSE","level":0,"tm":true,"breeding":false},{"name":"TOXIC","level":0,"tm":true,"breeding":false},{"name":"HIDDEN POWER","level":0,"tm":true,"breeding":false},{"name":"SNORE","level":0,"tm":true,"breeding":false},{"name":"BLIZZARD","level":0,"tm":true,"breeding":false},{"name":"ICY WIND","level":0,"tm":true,"breeding":false},{"name":"PROTECT","level":0,"tm":true,"breeding":false},{"name":"RAIN DANCE","level":0,"tm":true,"breeding":false},{"name":"ENDURE","level":0,"tm":true,"breeding":false},{"name":"FRUSTRATION","level":0,"tm":true,"breeding":false},{"name":"RETURN","level":0,"tm":true,"breeding":false},{"name":"MUD-SLAP","level":0,"tm":true,"breeding":false},{"name":"DOUBLE TEAM","level":0,"tm":true,"breeding":false},{"name":"SWAGGER","level":0,"tm":true,"breeding":false},{"name":"SLEEP TALK","level":0,"tm":true,"breeding":false},{"name":"SWIFT","level":0,"tm":true,"breeding":false},{"name":"REST","level":0,"tm":true,"breeding":false},{"name":"ATTRACT","level":0,"tm":true,"breeding":false},{"name":"SURF","level":0,"tm":true,"breeding":false},{"name":"WHIRLPOOL","level":0,"tm":true,"breeding":false},{"name":"WATERFALL","level":0,"tm":true,"breeding":false},{"name":"HAZE","level":0,"tm":false,"breeding":true},{"name":"HYDRO PUMP","level":0,"tm":false,"breeding":true},{"name":"SLAM","level":0,"tm":false,"breeding":true},{"name":"TWISTER","level":0,"tm":false,"breeding":true}],"colors":{"normal":[[0,0,0],[24,48,152],[160,128,144],[248,248,248]],"shiny":[[0,0,0],[49,140,255],[197,222,255],[255,255,255]]}}