{"id":24,"name":"ARBOK","gender":"equal","baseStats":[60,85,69,65,79,80],"experienceType":"mediumFast","experienceYield":147,"type1":"poison","type2":"none","eggGroups":["field","dragon"],"eggCycles":20,"catchRate":90,"wildFleeRate":0.0,"moves":[{"name":"WRAP","level":1,"tm":false,"breeding":false},{"name":"LEER","level":1,"tm":false,"breeding":false},{"name":"POISON STING","level":1,"tm":false,"breeding":false},{"name":"BITE","level":1,"tm":false,"breeding":false},{"name":"POISON STING","level":9,"tm":false,"breeding":false},{"name":"BITE","level":15,"tm":false,"breeding":false},{"name":"GLARE","level":25,"tm":false,"breeding":false},{"name":"SCREECH","level":33,"tm":false,"breeding":false},{"name":"ACID","level":43,"tm":false,"breeding":false},{"name":"HAZE","level":51,"tm":false,"breeding":false},{"name":"HEADBUTT","level":0,"tm":true,"breeding":false},{"name":"CURSE","level":0,"tm":true,"breeding":false},{"name":"TOXIC","level":0,"tm":true,"breeding":false},{"name":"HIDDEN POWER","level":0,"tm":true,"breeding":false},{"name":"SUNNY DAY","level":0,"tm":true,"breeding":false},{"name":"SNORE","level":0,"tm":true,"breeding":false},{"name":"HYPER BEAM","level":0,"tm":true,"breeding":false},{"name":"PROTECT","level":0,"tm":true,"breeding":false},{"name":"GIGA DRAIN","level":0,"tm":true,"breeding":false},{"name":"ENDURE","level":0,"tm":true,"breeding":false},{"name":"FRUSTRATION","level":0,"tm":true,"breeding":false},{"name":"EARTHQUAKE","level":0,"tm":true,"breeding":false},{"name":"RETURN","level":0,"tm":true,"breeding":false},{"name":"DIG","level":0,"tm":true,"breeding":false},{"name":"DOUBLE TEAM","level":0,"tm":true,"breeding":false},{"name":"SWAGGER","level":0,"tm":true,"breeding":false},{"name":"SLEEP TALK","level":0,"tm":true,"breeding":false},{"name":"SLUDGE BOMB","level":0,"tm":true,"breeding":false},{"name":"REST","level":0,"tm":true,"breeding":false},{"name":"ATTRACT","level":0,"tm":true,"breeding":false},{"name":"THIEF","level":0,"tm":true,"breeding":false},{"name":"STRENGTH","level":0,"tm":true,"breeding":false},{"name":"BEAT UP","level":0,"tm":false,"breeding":true},{"name":"CRUNCH","level":0,"tm":false,"breeding":true},{"name":"PURSUIT","level":0,"tm":false,"breeding":true},{"name":"SLAM","level":0,"tm":false,"breeding":true},{"name":"SPITE","level":0,"tm":false,"breeding":true}],"colors":{"normal":[[0,0,0],[176,32,72],[144,64,152],[248,248,248]],"shiny":[[0,0,0],[151,159,95],[167,87,247],[255,255,255]]}}